skellytracker/RUN_ME.py
skellytracker/SINGLE_IMAGE_RUN.py
skellytracker/__init__.py
skellytracker/__main__.py
skellytracker/process_folder_of_videos.py
skellytracker/scripts/blendshapes_to_csv.py
skellytracker/system/__init__.py
skellytracker/system/constants.py
skellytracker/system/default_paths.py
skellytracker/system/logging_configuration.py
skellytracker/tests/__init__.py
skellytracker/tests/conftest.py
skellytracker/tests/test_brightest_point_tracker.py
skellytracker/tests/test_charuco_tracker.py
skellytracker/tests/test_mediapipe_holistic_tracker.py
skellytracker/tests/test_yolo_mediapipe_combo_tracker.py
skellytracker/tests/test_yolo_object_tracker.py
skellytracker/tests/test_yolo_pose_tracker.py
skellytracker/trackers/__init__.py
skellytracker/trackers/base_tracker/__init__.py
skellytracker/trackers/base_tracker/base_recorder.py
skellytracker/trackers/base_tracker/base_tracker.py
skellytracker/trackers/base_tracker/base_tracking_params.py
skellytracker/trackers/base_tracker/model_info.py
skellytracker/trackers/base_tracker/tracked_object.py
skellytracker/trackers/base_tracker/video_handler.py
skellytracker/trackers/bright_point_tracker/__init__.py
skellytracker/trackers/bright_point_tracker/brightest_point_recorder.py
skellytracker/trackers/bright_point_tracker/brightest_point_tracker.py
skellytracker/trackers/charuco_tracker/charuco_model_info.py
skellytracker/trackers/charuco_tracker/charuco_recorder.py
skellytracker/trackers/charuco_tracker/charuco_tracker.py
skellytracker/trackers/demo_viewers/image_demo_viewer.py
skellytracker/trackers/demo_viewers/webcam_demo_viewer.py
skellytracker/trackers/mediapipe_blendshape_tracker/mediapipe_blendshape_model_info.py
skellytracker/trackers/mediapipe_blendshape_tracker/mediapipe_blendshape_recorder.py
skellytracker/trackers/mediapipe_blendshape_tracker/mediapipe_blendshape_tracker.py
skellytracker/trackers/mediapipe_tracker/mediapipe_holistic_recorder.py
skellytracker-2025.10.1024.dist-info/entry_points.txt
skellytracker-2025.10.1024.dist-info/licenses/LICENSE
skellytracker-2025.10.1024.dist-info/WHEEL
skellytracker-2025.10.1024.dist-info/METADATA
skellytracker-2025.10.1024.dist-info/RECORD
