Metadata-Version: 2.4
Name: skellytracker
Version: 2025.10.1024
Summary: Top-level package for skellytracker
Keywords: camera,stream,video,image,opencv,skelly,freemocap,motion capture,synchronization,computer vision
Author-email: Skelly FreeMoCap <info@freemocap.org>
Requires-Python: >=3.9,<3.13
Classifier: License :: OSI Approved :: GNU Affero General Public License v3 or later (AGPLv3+)
Classifier: Intended Audience :: Developers
Classifier: Intended Audience :: Education
Classifier: Intended Audience :: Healthcare Industry
Classifier: Intended Audience :: Science/Research
Classifier: Intended Audience :: End Users/Desktop
Classifier: Intended Audience :: Other Audience
Classifier: Natural Language :: English
Classifier: Operating System :: OS Independent
Classifier: Programming Language :: Python :: 3
Classifier: Programming Language :: Python :: 3.8
Classifier: Programming Language :: Python :: 3.9
Classifier: Programming Language :: Python :: 3.10
Classifier: Programming Language :: Python :: 3.11
Classifier: Topic :: Software Development :: Libraries :: Python Modules
Classifier: Topic :: Utilities
Classifier: Topic :: Multimedia :: Video
Classifier: Topic :: Multimedia :: Video :: Capture
Classifier: Topic :: Multimedia :: Video :: Display
Classifier: Topic :: Scientific/Engineering
Classifier: Topic :: Scientific/Engineering :: Image Processing
Classifier: Topic :: Scientific/Engineering :: Visualization
Classifier: Topic :: Scientific/Engineering :: Human Machine Interfaces
Classifier: Topic :: System :: Hardware
Classifier: Topic :: System :: Hardware :: Universal Serial Bus (USB)
Classifier: Topic :: System :: Hardware :: Universal Serial Bus (USB) :: Video (UVC)
License-File: LICENSE
Requires-Dist: opencv-contrib-python==4.8.*
Requires-Dist: pydantic==2.*
Requires-Dist: numpy<2
Requires-Dist: tqdm==4.*
Requires-Dist: ultralytics~=8.3.132 ; extra == "all"
Requires-Dist: torch==2.8.* ; extra == "all"
Requires-Dist: torchvision==0.23.* ; extra == "all"
Requires-Dist: mediapipe==0.10.14 ; extra == "all"
Requires-Dist: black ; extra == "dev"
Requires-Dist: bumpver ; extra == "dev"
Requires-Dist: isort ; extra == "dev"
Requires-Dist: pip-tools ; extra == "dev"
Requires-Dist: pytest ; extra == "dev"
Requires-Dist: ruff ; extra == "dev"
Requires-Dist: mediapipe==0.10.14 ; extra == "mediapipe"
Requires-Dist: ultralytics~=8.3.132 ; extra == "yolo"
Requires-Dist: torch==2.8.* ; extra == "yolo"
Requires-Dist: torchvision==0.23.* ; extra == "yolo"
Project-URL: Homepage, https://github.com/freemocap/skellytracker
Provides-Extra: all
Provides-Extra: dev
Provides-Extra: mediapipe
Provides-Extra: yolo
